Metadata-Version: 1.1
Name: gstreamer-player
Version: 1.1.1
Summary: Python 3 wrapper for playing media via gstreamer
Home-page: https://github.com/happyleavesaoc/gstreamer-player/
Author: happyleaves
Author-email: happyleaves.tfr@gmail.com
License: MIT
Platform: UNKNOWN
Classifier: License :: OSI Approved :: MIT License
Classifier: Operating System :: OS Independent
Classifier: Programming Language :: Python :: 3
